simple/__init__.py
simple/simple.py
simple_fast_python-1.0.dist-info/METADATA
simple_fast_python-1.0.dist-info/WHEEL
simple_fast_python-1.0.dist-info/top_level.txt
simple_fast_python-1.0.dist-info/RECORD
