Metadata-Version: 2.1
Name: simple-fast-python
Version: 1.0
Summary: An implementation of the SiMPle-Fast algorithm
Home-page: https://github.com/acmiyaguchi/simple-fast-python
Author: Anthony Miyaguchi
Author-email: acmiyaguchi@gmail.com
License: UNKNOWN
Platform: UNKNOWN
Requires-Dist: numpy
